bank_account_validator/__init__.py
bank_account_validator/core.py
bank_account_validator/exceptions.py
bank_account_validator/utils.py
bank_account_validator-0.2.dist-info/LICENSE
bank_account_validator-0.2.dist-info/METADATA
bank_account_validator-0.2.dist-info/WHEEL
bank_account_validator-0.2.dist-info/top_level.txt
bank_account_validator-0.2.dist-info/RECORD
