Metadata-Version: 2.1
Name: bank-account-validator
Version: 0.2
Summary: Python implementation for bank account validation.
Home-page: UNKNOWN
Author: Filipe Waitman
Author-email: filwaitman@gmail.com
License: MIT
Project-URL: Source, https://github.com/filwaitman/bank-account-validator
Platform: UNKNOWN
Classifier: Development Status :: 4 - Beta
Classifier: Intended Audience :: Developers
Classifier: License :: OSI Approved :: MIT License
Classifier: Operating System :: OS Independent
Classifier: Programming Language :: Python
Classifier: Programming Language :: Python :: 2
Classifier: Programming Language :: Python :: 2.7
Classifier: Programming Language :: Python :: 3
Classifier: Programming Language :: Python :: 3.6
Classifier: Programming Language :: Python :: 3.7
Classifier: Programming Language :: Python :: 3.8
